[{"id": "170959118931066880", "username": "Phoenix", "avatar": "2319ea5054607f5e64738014b43cf809", "avatar_decoration": null, "discriminator": "7449", "public_flags": 0}, {"id": "170941289330769921", "username": "Morat", "avatar": "9143efbffff1985922d074e44ec4b747", "avatar_decoration": null, "discriminator": "5492", "public_flags": 128}, {"id": "251419764356808704", "username": "Shmilll3", "avatar": "7387bdebe39e5fa97592678106cebf24", "avatar_decoration": null, "discriminator": "2939", "public_flags": 0}, {"id": "194042768253911040", "username": "Sayrin", "avatar": "1b3919f296777f1b175a6f0f7e7b1d73", "avatar_decoration": null, "discriminator": "1142", "public_flags": 0}, {"id": "210694248482340864", "username": "Dor Alon", "avatar": "af24ccfb8ee414e618b34697e4eb1bca", "avatar_decoration": null, "discriminator": "1516", "public_flags": 0}, {"id": "221997679981363200", "username": "supernova", "avatar": "0c66fd252c8dd23dca58c1dc27fa109c", "avatar_decoration": null, "discriminator": "3435", "public_flags": 0}, {"id": "295918070524936193", "username": "orvax", "avatar": null, "avatar_decoration": null, "discriminator": "0182", "public_flags": 0}, {"id": "288374758427459585", "username": "Insulin", "avatar": "193e27eb96527f4c7a6fe1a813228929", "avatar_decoration": null, "discriminator": "5215", "public_flags": 0}, {"id": "378526044006645761", "username": "Mr.Spetznaz", "avatar": "01d55a9fad7751918960d77f9e822fea", "avatar_decoration": null, "discriminator": "6342", "public_flags": 0}, {"id": "294801834537910273", "username": "Tamir", "avatar": "5c87fa059f21e12e5535a548a494facc", "avatar_decoration": null, "discriminator": "9267", "public_flags": 0}, {"id": "426081050842890250", "username": "Adi tangy", "avatar": null, "avatar_decoration": null, "discriminator": "8101", "public_flags": 0}, {"id": "334028207621668875", "username": "its_me_mario", "avatar": "504a1a07b009cbdacca305ebc529fd8b", "avatar_decoration": null, "discriminator": "9999", "public_flags": 0}, {"id": "284369265165991936", "username": "yanive55", "avatar": "4f195e11cc271a8e592a1a20b4b94f5b", "avatar_decoration": null, "discriminator": "5873", "public_flags": 0}, {"id": "317587596312182784", "username": "Griffhawkk", "avatar": "6e7c3af8bff790409985f28a6a496f50", "avatar_decoration": null, "discriminator": "3029", "public_flags": 0}, {"id": "322756511220760576", "username": "Wonder", "avatar": "5e2c94da78aba6661ad66d0d7615e048", "avatar_decoration": null, "discriminator": "1276", "public_flags": 0}, {"id": "296988027505606658", "username": "erez_berez", "avatar": "11c3bd6ce048ba23af46971999e7157e", "avatar_decoration": null, "discriminator": "7502", "public_flags": 0}, {"id": "261861771487346708", "username": "_Zeus_", "avatar": "008f0e0f32ef06abf199146f82dca69f", "avatar_decoration": null, "discriminator": "0122", "public_flags": 0}, {"id": "284345424704307220", "username": "Gr33tings", "avatar": "ef6c9b0adaa60c9052615672c74b2710", "avatar_decoration": null, "discriminator": "2828", "public_flags": 0}, {"id": "219547356889088000", "username": "Pluto", "avatar": "de6a31f7b0c12e4d98eb5e5d0ee8731e", "avatar_decoration": null, "discriminator": "9154", "public_flags": 256}]