[{"id": "278540363373871104", "username": "MrItay", "avatar": "b0ef630ee8b7ef9a41e1ba55b1f60e77", "avatar_decoration": null, "discriminator": "2878", "public_flags": 128}, {"id": "255728342160900097", "username": "\ud835\ude8d\ud835\udff7\ud835\ude97\ud835\ude98\ud835\ude97\ud835\ude95\ud835\udea2", "avatar": "2fb3bd8ad03f38f8d0be9629f7dd0918", "avatar_decoration": null, "discriminator": "7545", "public_flags": 128}, {"id": "279254941850271746", "username": "ran42", "avatar": null, "avatar_decoration": null, "discriminator": "1508", "public_flags": 0}, {"id": "330394362108182529", "username": "Kantes", "avatar": "57acae9ba3b0667562b32f4e0afd41fd", "avatar_decoration": null, "discriminator": "0275", "public_flags": 0}, {"id": "576021145518735372", "username": "nmy2130", "avatar": "b3f4084d4bea450871ea1d588b2b5ecf", "avatar_decoration": null, "discriminator": "8225", "public_flags": 0}, {"id": "582308803937042458", "username": "shiraccri", "avatar": "cb44844e334ea7a92e8577f2d55336dd", "avatar_decoration": null, "discriminator": "3411", "public_flags": 0}, {"id": "669645297290575902", "username": "tamir2001", "avatar": "bb5ad54c85a0712bd625afa7f45b6477", "avatar_decoration": null, "discriminator": "2281", "public_flags": 0}]